[
  {
    "_disabled": "false",
    "pkg": "almalinux",
    "pkg_family": "almalinux",
    "pkg_id": "github.com.AlmaLinux.docker-images",
    "pkg_type": "static",
    "pkg_webpage": "https://pkgs.pkgforge.dev/repo/soarpkgs/docker-images/almalinux/almalinux",
    "bincache": "ghcr.io/pkgforge/bincache/almalinux/official/almalinux",
    "build_script": "https://github.com/pkgforge/soarpkgs/blob/main/binaries/almalinux/static.official.stable.yaml",
    "category": [
      "ConsoleOnly",
      "Utility"
    ],
    "description": "Portable Ephemeral AlmaLinux Docker Image (DockerC)",
    "download_url": "https://soarpkgs.pkgforge.dev/binaries/almalinux/static.official.stable.yaml",
    "homepage": [
      "https://wiki.almalinux.org/containers/docker-images.html"
    ],
    "host": [
      "aarch64-linux",
      "x86_64-linux"
    ],
    "license": [
      "MIT"
    ],
    "maintainer": [
      "Azathothas (https://github.com/Azathothas)"
    ],
    "note": [
      "[DO NOT RUN] (Meant for pkgforge CI Only)",
      "Created using DockerC, might require ROOT (Details: https://hub.docker.com/_/almalinux)"
    ],
    "provides": [
      "almalinux",
      "almalinux-minimal"
    ],
    "src_url": [
      "https://github.com/AlmaLinux/docker-images"
    ],
    "tag": [
      "almalinux",
      "docker"
    ]
  },
  {
    "_disabled": "false",
    "pkg": "alpine",
    "pkg_family": "alpine",
    "pkg_id": "github.com.alpinelinux.docker-alpine",
    "pkg_type": "static",
    "pkg_webpage": "https://pkgs.pkgforge.dev/repo/soarpkgs/docker-alpine/alpine/alpine",
    "bincache": "ghcr.io/pkgforge/bincache/alpine/official/alpine",
    "build_script": "https://github.com/pkgforge/soarpkgs/blob/main/binaries/alpine/static.official.stable.yaml",
    "category": [
      "ConsoleOnly",
      "Utility"
    ],
    "description": "Portable Ephemeral Alpine Linux Docker Image (DockerC)",
    "download_url": "https://soarpkgs.pkgforge.dev/binaries/alpine/static.official.stable.yaml",
    "homepage": [
      "https://github.com/alpinelinux/docker-alpine"
    ],
    "host": [
      "aarch64-linux",
      "x86_64-linux"
    ],
    "license": [
      "MIT"
    ],
    "maintainer": [
      "Azathothas (https://github.com/Azathothas)"
    ],
    "note": [
      "[DO NOT RUN] (Meant for pkgforge CI Only)",
      "Created using DockerC, might require ROOT (Details: https://hub.docker.com/_/alpine)"
    ],
    "provides": [
      "alpine"
    ],
    "repology": [
      "alpine"
    ],
    "src_url": [
      "https://github.com/alpinelinux/docker-alpine"
    ],
    "tag": [
      "alpinelinux",
      "docker"
    ]
  },
  {
    "_disabled": "false",
    "pkg": "amazonlinux",
    "pkg_family": "amazonlinux",
    "pkg_id": "github.com.aws.amazon-linux-docker-images",
    "pkg_type": "static",
    "pkg_webpage": "https://pkgs.pkgforge.dev/repo/soarpkgs/docker-images/amazonlinux/amazonlinux",
    "bincache": "ghcr.io/pkgforge/bincache/amazonlinux/official/amazonlinux",
    "build_script": "https://github.com/pkgforge/soarpkgs/blob/main/binaries/amazonlinux/static.official.stable.yaml",
    "category": [
      "ConsoleOnly",
      "Utility"
    ],
    "description": "Portable Ephemeral AmazonLinux Docker Image (DockerC)",
    "download_url": "https://soarpkgs.pkgforge.dev/binaries/amazonlinux/static.official.stable.yaml",
    "homepage": [
      "https://github.com/aws/amazon-linux-docker-images"
    ],
    "host": [
      "aarch64-linux",
      "x86_64-linux"
    ],
    "license": [
      "GPL-2.0"
    ],
    "maintainer": [
      "Azathothas (https://github.com/Azathothas)"
    ],
    "note": [
      "[DO NOT RUN] (Meant for pkgforge CI Only)",
      "Created using DockerC, might require ROOT (Details: https://hub.docker.com/_/amazonlinux)"
    ],
    "provides": [
      "amazonlinux"
    ],
    "src_url": [
      "https://github.com/aws/amazon-linux-docker-images"
    ],
    "tag": [
      "Utility"
    ]
  },
  {
    "_disabled": "false",
    "pkg": "apk-static",
    "pkg_family": "apk-static",
    "pkg_id": "gitlab.alpinelinux.org.alpine.apk-tools",
    "pkg_type": "static",
    "pkg_webpage": "https://pkgs.pkgforge.dev/repo/soarpkgs/apk-tools/apk-static/apk-static",
    "bincache": "ghcr.io/pkgforge/bincache/apk-static/official/apk-static",
    "build_script": "https://github.com/pkgforge/soarpkgs/blob/main/binaries/apk-static/static.official.stable.yaml",
    "category": [
      "ConsoleOnly",
      "Utility"
    ],
    "description": "Alpine Package Keeper (apk)",
    "distro_pkg": {
      "alpine": [
        "apk-tools"
      ],
      "archlinux": {
        "aur": [
          "apk-tools-git",
          "apk-tools-static-bin"
        ],
        "extra": [
          "apk-tools"
        ]
      },
      "nixpkgs": [
        "apk-tools"
      ]
    },
    "download_url": "https://soarpkgs.pkgforge.dev/binaries/apk-static/static.official.stable.yaml",
    "homepage": [
      "https://wiki.alpinelinux.org/wiki/Alpine_Package_Keeper",
      "https://gitlab.alpinelinux.org/alpine/apk-tools",
      "http://git.alpinelinux.org/cgit/apk-tools"
    ],
    "host": [
      "aarch64-linux",
      "x86_64-linux"
    ],
    "license": [
      "GPL-2.0"
    ],
    "maintainer": [
      "Azathothas (https://github.com/Azathothas)"
    ],
    "note": [
      "[DO NOT RUN] (Meant for pkgforge CI Only)",
      "Pre Built Binary Fetched from Upstream. Check/Report @ https://gitlab.alpinelinux.org/alpine/apk-tools"
    ],
    "provides": [
      "apk-static:apk"
    ],
    "repology": [
      "apk-static"
    ],
    "src_url": [
      "https://gitlab.alpinelinux.org/alpine/apk-tools"
    ],
    "tag": [
      "alpine",
      "package-manager"
    ],
    "version": "v2.14.9"
  },
  {
    "_disabled": "false",
    "pkg": "archlinux",
    "pkg_family": "archlinux",
    "pkg_id": "github.com.Azathothas.docker-archlinux",
    "pkg_type": "static",
    "pkg_webpage": "https://pkgs.pkgforge.dev/repo/soarpkgs/docker-archlinux/archlinux/archlinux",
    "bincache": "ghcr.io/pkgforge/bincache/archlinux/azathothas/archlinux",
    "build_script": "https://github.com/pkgforge/soarpkgs/blob/main/binaries/archlinux/static.azathothas.stable.yaml",
    "category": [
      "ConsoleOnly",
      "Utility"
    ],
    "description": "Portable Ephemeral ArchLinux Docker Image (DockerC)",
    "download_url": "https://soarpkgs.pkgforge.dev/binaries/archlinux/static.azathothas.stable.yaml",
    "homepage": [
      "https://wiki.archlinux.org/title/Docker"
    ],
    "host": [
      "aarch64-linux",
      "x86_64-linux"
    ],
    "license": [
      "MIT"
    ],
    "maintainer": [
      "Azathothas (https://github.com/Azathothas)"
    ],
    "note": [
      "[DO NOT RUN] (Meant for pkgforge CI Only)",
      "Created using DockerC, might require ROOT (Details: https://hub.docker.com/_/archlinux)"
    ],
    "provides": [
      "archlinux"
    ],
    "src_url": [
      "https://github.com/pkgforge-dev/docker-archlinux"
    ],
    "tag": [
      "archlinux"
    ]
  },
  {
    "_disabled": "false",
    "pkg": "aria2",
    "pkg_family": "aria2",
    "pkg_id": "github.com.aria2.aria2",
    "pkg_type": "static",
    "pkg_webpage": "https://pkgs.pkgforge.dev/repo/soarpkgs/aria2-aria2/aria2/aria2",
    "bincache": "ghcr.io/pkgforge/bincache/aria2/abcfy2/continuous",
    "build_script": "https://github.com/pkgforge/soarpkgs/blob/main/binaries/aria2/static.abcfy2.continuous.yaml",
    "category": [
      "ConsoleOnly",
      "Utility"
    ],
    "description": "A multi-protocol (HTTP/HTTPS, FTP, SFTP, BitTorrent & Metalink) & multi-source command-line download utility",
    "distro_pkg": {
      "alpine": [
        "aria2"
      ],
      "archlinux": {
        "aur": [
          "aria2-fast",
          "aria2-git"
        ],
        "extra": [
          "aria2"
        ]
      },
      "debian": [
        "aria2"
      ],
      "nixpkgs": [
        "aria",
        "aria2"
      ]
    },
    "download_url": "https://soarpkgs.pkgforge.dev/binaries/aria2/static.abcfy2.continuous.yaml",
    "homepage": [
      "https://aria2.github.io",
      "https://github.com/aria2/aria2",
      "https://aria2.sourceforge.net",
      "https://sourceforge.net/projects/aria2"
    ],
    "host": [
      "aarch64-linux",
      "x86_64-linux"
    ],
    "license": [
      "GPL-2.0"
    ],
    "maintainer": [
      "Azathothas (https://github.com/Azathothas)"
    ],
    "note": [
      "[DO NOT RUN] (Meant for pkgforge CI Only)",
      "This is a continuous build",
      "Community Created Binary. Check/Report @ https://github.com/abcfy2/aria2-static-build"
    ],
    "provides": [
      "aria2:aria2c"
    ],
    "repology": [
      "aria2"
    ],
    "src_url": [
      "https://github.com/abcfy2/aria2-static-build"
    ],
    "tag": [
      "bittorrent",
      "downloader"
    ],
    "version": "250118T141142"
  },
  {
    "_disabled": "false",
    "pkg": "bucketloot",
    "pkg_family": "bucketloot",
    "pkg_id": "github.com.redhuntlabs.BucketLoot",
    "pkg_type": "static",
    "pkg_webpage": "https://pkgs.pkgforge.dev/repo/soarpkgs/redhuntlabs-bucketloot/bucketloot/bucketloot",
    "bincache": "ghcr.io/pkgforge/bincache/bucketloot/official/bucketloot",
    "build_script": "https://github.com/pkgforge/soarpkgs/blob/main/binaries/bucketloot/static.official.source.yaml",
    "category": [
      "ConsoleOnly",
      "Utility"
    ],
    "description": "Automated S3-compatible bucket inspector",
    "download_url": "https://soarpkgs.pkgforge.dev/binaries/bucketloot/static.official.source.yaml",
    "homepage": [
      "https://github.com/redhuntlabs/BucketLoot"
    ],
    "host": [
      "aarch64-linux",
      "x86_64-linux"
    ],
    "maintainer": [
      "Azathothas (https://github.com/Azathothas)"
    ],
    "note": [
      "[DO NOT RUN] (Meant for pkgforge CI Only)",
      "Built From Source (Latest Git HEAD). Check/Report @ https://github.com/redhuntlabs/BucketLoot"
    ],
    "provides": [
      "bucketloot"
    ],
    "src_url": [
      "https://github.com/redhuntlabs/BucketLoot"
    ],
    "tag": [
      "bugbounty",
      "cloud",
      "s3",
      "secret-scanning"
    ],
    "version": "HEAD-69949e0-250122T104826"
  },
  {
    "_disabled": "false",
    "pkg": "caddy",
    "pkg_family": "caddy",
    "pkg_id": "github.com.caddyserver.caddy",
    "pkg_type": "static",
    "pkg_webpage": "https://pkgs.pkgforge.dev/repo/soarpkgs/caddyserver-caddy/caddy/caddy",
    "build_script": "https://github.com/pkgforge/soarpkgs/blob/main/binaries/caddy/static.official.stable.yaml",
    "category": [
      "ConsoleOnly",
      "Utility"
    ],
    "description": "A powerful, enterprise-ready, and extensible HTTP/2 + HTTP/3 web server with automatic HTTPS",
    "distro_pkg": {
      "alpine": [
        "caddy"
      ],
      "archlinux": {
        "aur": [
          "caddy-git"
        ],
        "extra": [
          "caddy"
        ]
      },
      "debian": [
        "caddy"
      ],
      "homebrew": [
        "caddy"
      ],
      "nixpkgs": [
        "caddy"
      ]
    },
    "download_url": "https://soarpkgs.pkgforge.dev/binaries/caddy/static.official.stable.yaml",
    "homepage": [
      "https://caddyserver.com",
      "https://github.com/caddyserver/caddy"
    ],
    "host": [
      "aarch64-linux",
      "x86_64-linux"
    ],
    "license": [
      "Apache-2.0"
    ],
    "maintainer": [
      "Azathothas (https://github.com/Azathothas)"
    ],
    "note": [
      "[DO NOT RUN] (Meant for pkgforge CI Only)",
      "Pre Built Binary Fetched from Upstream. Check/Report @ https://github.com/caddyserver/caddy"
    ],
    "provides": [
      "caddy"
    ],
    "repology": [
      "caddy"
    ],
    "src_url": [
      "https://github.com/caddyserver/caddy"
    ],
    "tag": [
      "caddy",
      "server",
      "nginx"
    ],
    "version": "v2.9.1"
  },
  {
    "_disabled": "false",
    "pkg": "clearlinux",
    "pkg_family": "clearlinux",
    "pkg_id": "github.com.clearlinux.docker-brew-clearlinux",
    "pkg_type": "static",
    "pkg_webpage": "https://pkgs.pkgforge.dev/repo/soarpkgs/brew-clearlinux/clearlinux/clearlinux",
    "bincache": "ghcr.io/pkgforge/bincache/clearlinux/official/clearlinux",
    "build_script": "https://github.com/pkgforge/soarpkgs/blob/main/binaries/clearlinux/static.official.stable.yaml",
    "category": [
      "ConsoleOnly",
      "Utility"
    ],
    "description": "Portable Ephemeral ClearLinux Docker Image (DockerC)",
    "download_url": "https://soarpkgs.pkgforge.dev/binaries/clearlinux/static.official.stable.yaml",
    "homepage": [
      "https://github.com/clearlinux/docker-brew-clearlinux"
    ],
    "host": [
      "x86_64-linux"
    ],
    "license": [
      "Apache-2.0"
    ],
    "maintainer": [
      "Azathothas (https://github.com/Azathothas)"
    ],
    "note": [
      "[DO NOT RUN] (Meant for pkgforge CI Only)",
      "Created using DockerC, might require ROOT (Details: https://hub.docker.com/_/clearlinux)"
    ],
    "provides": [
      "clearlinux"
    ],
    "repology": [
      "clearlinux"
    ],
    "src_url": [
      "https://github.com/clearlinux/docker-brew-clearlinux"
    ],
    "tag": [
      "clearlinux",
      "docker"
    ]
  },
  {
    "_disabled": "false",
    "pkg": "cobalt-cli",
    "pkg_family": "cobalt-cli",
    "pkg_id": "github.com.lostdusty.cobalt",
    "pkg_type": "static",
    "pkg_webpage": "https://pkgs.pkgforge.dev/repo/soarpkgs/lostdusty-cobalt/cobalt-cli/cobalt-cli",
    "bincache": "ghcr.io/pkgforge/bincache/cobalt-cli/official/cobalt",
    "build_script": "https://github.com/pkgforge/soarpkgs/blob/main/binaries/cobalt-cli/static.official.source.yaml",
    "category": [
      "ConsoleOnly",
      "Utility"
    ],
    "description": "Command-line interface wrapper for https://cobalt.tools",
    "distro_pkg": {
      "archlinux": {
        "aur": [
          "cobalt-cli-git"
        ]
      }
    },
    "download_url": "https://soarpkgs.pkgforge.dev/binaries/cobalt-cli/static.official.source.yaml",
    "homepage": [
      "https://cobalt.tools",
      "https://github.com/lostdusty/cobalt"
    ],
    "host": [
      "aarch64-linux",
      "x86_64-linux"
    ],
    "license": [
      "MIT"
    ],
    "maintainer": [
      "Azathothas (https://github.com/Azathothas)"
    ],
    "note": [
      "[DO NOT RUN] (Meant for pkgforge CI Only)",
      "Built From Source (Latest Git HEAD). Check/Report @ https://github.com/lostdusty/cobalt"
    ],
    "provides": [
      "cobalt:cobalt-cli"
    ],
    "repology": [
      "cobalt-cli"
    ],
    "src_url": [
      "https://github.com/lostdusty/cobalt"
    ],
    "tag": [
      "cobalt",
      "cobalt-tools",
      "downloader",
      "youtube",
      "ytdlp"
    ],
    "version": "HEAD-ef68775-250118T170224"
  },
  {
    "_disabled": "false",
    "pkg": "cocogitto",
    "pkg_family": "cocogitto",
    "pkg_id": "github.com.cocogitto.cocogitto",
    "pkg_type": "static",
    "pkg_webpage": "https://pkgs.pkgforge.dev/repo/soarpkgs/cocogitto-cocogitto/cocogitto/cocogitto",
    "bincache": "ghcr.io/pkgforge/bincache/cocogitto/official/cocogitto",
    "build_script": "https://github.com/pkgforge/soarpkgs/blob/main/binaries/cocogitto/static.official.source.yaml",
    "category": [
      "ConsoleOnly",
      "Utility"
    ],
    "description": "Set of CLI tools for the conventional commit and semver specifications",
    "distro_pkg": {
      "alpine": [
        "cocogitto"
      ],
      "archlinux": {
        "aur": [
          "cocogitto-git"
        ],
        "extra": [
          "cocogitto"
        ]
      },
      "nixpkgs": [
        "cocogitto"
      ]
    },
    "download_url": "https://soarpkgs.pkgforge.dev/binaries/cocogitto/static.official.source.yaml",
    "homepage": [
      "https://github.com/cocogitto/cocogitto",
      "https://docs.cocogitto.io"
    ],
    "host": [
      "aarch64-linux",
      "x86_64-linux"
    ],
    "license": [
      "MIT"
    ],
    "maintainer": [
      "Azathothas (https://github.com/Azathothas)"
    ],
    "note": [
      "[DO NOT RUN] (Meant for pkgforge CI Only)",
      "Built From Source (Latest Git HEAD). Check/Report @ https://github.com/cocogitto/cocogitto"
    ],
    "provides": [
      "cocogitto==cog"
    ],
    "repology": [
      "cocogitto"
    ],
    "src_url": [
      "https://github.com/cocogitto/cocogitto"
    ],
    "tag": [
      "changelog",
      "git-commit"
    ],
    "version": "HEAD-f8cfa57-250111T105227"
  },
  {
    "_disabled": "false",
    "pkg": "czkawka",
    "pkg_family": "czkawka",
    "pkg_id": "github.com.qarmin.czkawka",
    "pkg_type": "static",
    "pkg_webpage": "https://pkgs.pkgforge.dev/repo/soarpkgs/qarmin-czkawka/czkawka/czkawka",
    "bincache": "ghcr.io/pkgforge/bincache/czkawka/official/czkawka-cli",
    "build_script": "https://github.com/pkgforge/soarpkgs/blob/main/binaries/czkawka/static.official.source.yaml",
    "category": [
      "ConsoleOnly",
      "Utility"
    ],
    "description": "Multi functional app to find duplicates, empty folders, similar images etc",
    "distro_pkg": {
      "alpine": [
        "czkawka"
      ],
      "archlinux": {
        "aur": [
          "czkawka",
          "czkawka-cli-bin"
        ]
      },
      "nixpkgs": [
        "czkawka"
      ]
    },
    "download_url": "https://soarpkgs.pkgforge.dev/binaries/czkawka/static.official.source.yaml",
    "homepage": [
      "https://github.com/qarmin/czkawka"
    ],
    "host": [
      "aarch64-linux",
      "x86_64-linux"
    ],
    "license": [
      "MIT"
    ],
    "maintainer": [
      "Azathothas (https://github.com/Azathothas)"
    ],
    "note": [
      "[DO NOT RUN] (Meant for pkgforge CI Only)",
      "Built From Source (Latest Git HEAD). Check/Report @ https://github.com/qarmin/czkawka"
    ],
    "provides": [
      "czkawka-cli:czkawka_cli"
    ],
    "repology": [
      "czkawka"
    ],
    "src_url": [
      "https://github.com/qarmin/czkawka"
    ],
    "tag": [
      "cleaner"
    ],
    "version": "HEAD-1a10059-250120T213625"
  },
  {
    "_disabled": "false",
    "pkg": "ghfetch",
    "pkg_family": "ghfetch",
    "pkg_id": "github.com.orangekame3.ghfetch",
    "pkg_type": "static",
    "pkg_webpage": "https://pkgs.pkgforge.dev/repo/soarpkgs/orangekame3-ghfetch/ghfetch/ghfetch",
    "bincache": "ghcr.io/pkgforge/bincache/ghfetch/official/ghfetch",
    "build_script": "https://github.com/pkgforge/soarpkgs/blob/main/binaries/ghfetch/static.official.source.yaml",
    "category": [
      "ConsoleOnly",
      "Utility"
    ],
    "description": "CLI tool to fetch GitHub user information and show like neofetch",
    "distro_pkg": {
      "archlinux": {
        "aur": [
          "ghfetch",
          "ghfetch-git"
        ]
      },
      "nixpkgs": [
        "ghfetch"
      ]
    },
    "download_url": "https://soarpkgs.pkgforge.dev/binaries/ghfetch/static.official.source.yaml",
    "homepage": [
      "https://github.com/orangekame3/ghfetch"
    ],
    "host": [
      "aarch64-linux",
      "x86_64-linux"
    ],
    "license": [
      "MIT"
    ],
    "maintainer": [
      "Azathothas (https://github.com/Azathothas)"
    ],
    "note": [
      "[DO NOT RUN] (Meant for pkgforge CI Only)",
      "Built From Source (Latest Git HEAD). Check/Report @ https://github.com/orangekame3/ghfetch"
    ],
    "provides": [
      "ghfetch"
    ],
    "repology": [
      "ghfetch"
    ],
    "src_url": [
      "https://github.com/orangekame3/ghfetch"
    ],
    "tag": [
      "github"
    ],
    "version": "HEAD-7e2326b-250122T120313"
  },
  {
    "_disabled": "false",
    "pkg": "gitui",
    "pkg_family": "gitui",
    "pkg_id": "github.com.extrawurst.gitui",
    "pkg_type": "static",
    "pkg_webpage": "https://pkgs.pkgforge.dev/repo/soarpkgs/extrawurst-gitui/gitui/gitui",
    "bincache": "ghcr.io/pkgforge/bincache/gitui/official/gitui",
    "build_script": "https://github.com/pkgforge/soarpkgs/blob/main/binaries/gitui/static.official.source.yaml",
    "category": [
      "ConsoleOnly",
      "Utility"
    ],
    "description": "Blazing 💥 fast terminal-ui for git written in rust 🦀",
    "distro_pkg": {
      "alpine": [
        "gitui"
      ],
      "archlinux": {
        "aur": [
          "gitui-git"
        ],
        "extra": [
          "gitui"
        ]
      },
      "nixpkgs": [
        "gitui"
      ]
    },
    "download_url": "https://soarpkgs.pkgforge.dev/binaries/gitui/static.official.source.yaml",
    "homepage": [
      "https://github.com/extrawurst/gitui"
    ],
    "host": [
      "aarch64-linux",
      "x86_64-linux"
    ],
    "license": [
      "BSD",
      "MIT"
    ],
    "maintainer": [
      "Azathothas (https://github.com/Azathothas)"
    ],
    "note": [
      "[DO NOT RUN] (Meant for pkgforge CI Only)",
      "Built From Source (Latest Git HEAD). Check/Report @ https://github.com/extrawurst/gitui"
    ],
    "repology": [
      "gitui"
    ],
    "src_url": [
      "https://github.com/extrawurst/gitui"
    ],
    "tag": [
      "git",
      "tui"
    ],
    "version": "HEAD-58b4e2c-250121T120756"
  },
  {
    "_disabled": "false",
    "pkg": "hcloud",
    "pkg_family": "hcloud",
    "pkg_id": "github.com.hetznercloud.cli",
    "pkg_type": "static",
    "pkg_webpage": "https://pkgs.pkgforge.dev/repo/soarpkgs/hetznercloud-cli/hcloud/hcloud",
    "bincache": "ghcr.io/pkgforge/bincache/hcloud/official/hcloud",
    "build_script": "https://github.com/pkgforge/soarpkgs/blob/main/binaries/hcloud/static.official.stable.yaml",
    "category": [
      "ConsoleOnly",
      "Utility"
    ],
    "description": "A command-line interface for Hetzner Cloud",
    "distro_pkg": {
      "alpine": [
        "hcloud"
      ],
      "archlinux": {
        "extra": [
          "hcloud"
        ]
      },
      "homebrew": [
        "hcloud"
      ],
      "nixpkgs": [
        "hcloud"
      ]
    },
    "download_url": "https://soarpkgs.pkgforge.dev/binaries/hcloud/static.official.stable.yaml",
    "homepage": [
      "https://github.com/hetznercloud/cli"
    ],
    "host": [
      "aarch64-linux",
      "x86_64-linux"
    ],
    "license": [
      "MIT"
    ],
    "maintainer": [
      "Azathothas (https://github.com/Azathothas)"
    ],
    "note": [
      "[DO NOT RUN] (Meant for pkgforge CI Only)",
      "Built From Source (Latest Git HEAD). Check/Report @ https://github.com/hetznercloud/cli"
    ],
    "provides": [
      "hcloud"
    ],
    "repology": [
      "hcloud"
    ],
    "src_url": [
      "https://github.com/hetznercloud/cli"
    ],
    "tag": [
      "hetzner"
    ],
    "version": "HEAD-6797c80-250122T131210"
  },
  {
    "_disabled": "false",
    "pkg": "noseyparker",
    "pkg_family": "noseyparker",
    "pkg_id": "github.com.praetorian-inc.noseyparker",
    "pkg_type": "static",
    "pkg_webpage": "https://pkgs.pkgforge.dev/repo/soarpkgs/inc-noseyparker/noseyparker/noseyparker",
    "bincache": "ghcr.io/pkgforge/bincache/noseyparker/official/noseyparker",
    "build_script": "https://github.com/pkgforge/soarpkgs/blob/main/binaries/noseyparker/static.official.source.yaml",
    "category": [
      "ConsoleOnly",
      "Utility"
    ],
    "description": "Finds secrets and sensitive information in textual data and Git history",
    "distro_pkg": {
      "archlinux": {
        "aur": [
          "noseyparker",
          "noseyparker-bin",
          "noseyparker-git"
        ]
      },
      "nixpkgs": [
        "noseyparker"
      ]
    },
    "download_url": "https://soarpkgs.pkgforge.dev/binaries/noseyparker/static.official.source.yaml",
    "homepage": [
      "https://github.com/praetorian-inc/noseyparker"
    ],
    "host": [
      "aarch64-linux",
      "x86_64-linux"
    ],
    "license": [
      "Apache-2"
    ],
    "maintainer": [
      "Azathothas (https://github.com/Azathothas)"
    ],
    "note": [
      "[DO NOT RUN] (Meant for pkgforge CI Only)",
      "Built From Source (Latest Git HEAD). Check/Report @ https://github.com/praetorian-inc/noseyparker"
    ],
    "provides": [
      "noseyparker",
      "noseyparker-cli"
    ],
    "repology": [
      "noseyparker"
    ],
    "src_url": [
      "https://github.com/praetorian-inc/noseyparker"
    ],
    "tag": [
      "scanner",
      "secret-detection",
      "security"
    ],
    "version": "HEAD-0092c80-250117T125303"
  },
  {
    "_disabled": "false",
    "pkg": "nuclei",
    "pkg_family": "nuclei",
    "pkg_id": "github.com.projectdiscovery.nuclei",
    "pkg_type": "static",
    "pkg_webpage": "https://pkgs.pkgforge.dev/repo/soarpkgs/projectdiscovery-nuclei/nuclei/nuclei",
    "bincache": "ghcr.io/pkgforge/bincache/nuclei/official/nuclei",
    "build_script": "https://github.com/pkgforge/soarpkgs/blob/main/binaries/nuclei/static.official.stable.yaml",
    "category": [
      "ConsoleOnly",
      "Utility"
    ],
    "description": "Fast and customizable vulnerability scanner based on simple YAML based DSL",
    "distro_pkg": {
      "archlinux": {
        "aur": [
          "nuclei",
          "nuclei-bin"
        ]
      },
      "homebrew": [
        "nuclei"
      ],
      "nixpkgs": [
        "nuclei"
      ]
    },
    "download_url": "https://soarpkgs.pkgforge.dev/binaries/nuclei/static.official.stable.yaml",
    "homepage": [
      "https://github.com/projectdiscovery/nuclei"
    ],
    "host": [
      "aarch64-linux",
      "x86_64-linux"
    ],
    "license": [
      "MIT"
    ],
    "maintainer": [
      "Azathothas (https://github.com/Azathothas)"
    ],
    "note": [
      "[DO NOT RUN] (Meant for pkgforge CI Only)",
      "Built From Source (Latest Git HEAD). Check/Report @ https://github.com/projectdiscovery/nuclei"
    ],
    "provides": [
      "nuclei"
    ],
    "repology": [
      "nuclei"
    ],
    "src_url": [
      "https://github.com/projectdiscovery/nuclei"
    ],
    "tag": [
      "bug-bounty",
      "recon",
      "security"
    ],
    "version": "HEAD-a0c3075-250122T120903"
  },
  {
    "_disabled": "false",
    "pkg": "nushell",
    "pkg_family": "nushell",
    "pkg_id": "github.com.nushell.nushell",
    "pkg_type": "static",
    "pkg_webpage": "https://pkgs.pkgforge.dev/repo/soarpkgs/nushell-nushell/nushell/nushell",
    "bincache": "ghcr.io/pkgforge/bincache/nushell/official/nu",
    "build_script": "https://github.com/pkgforge/soarpkgs/blob/main/binaries/nushell/static.official.source.yaml",
    "category": [
      "ConsoleOnly",
      "Utility"
    ],
    "description": "Shell with a focus on structured data",
    "distro_pkg": {
      "alpine": [
        "nushell"
      ],
      "archlinux": {
        "aur": [
          "nushell-git"
        ],
        "extra": [
          "nushell"
        ]
      },
      "nixpkgs": [
        "nushell"
      ]
    },
    "download_url": "https://soarpkgs.pkgforge.dev/binaries/nushell/static.official.source.yaml",
    "homepage": [
      "https://www.nushell.sh",
      "https://github.com/nushell/nushell"
    ],
    "host": [
      "aarch64-linux",
      "x86_64-linux"
    ],
    "license": [
      "0BSD",
      "ISC",
      "MIT"
    ],
    "maintainer": [
      "Azathothas (https://github.com/Azathothas)"
    ],
    "note": [
      "[DO NOT RUN] (Meant for pkgforge CI Only)",
      "Built From Source (Latest Git HEAD). Check/Report @ https://github.com/nushell/nushell"
    ],
    "provides": [
      "nu",
      "nushell"
    ],
    "repology": [
      "nushell"
    ],
    "src_url": [
      "https://github.com/nushell/nushell"
    ],
    "tag": [
      "shell"
    ],
    "version": "HEAD-84c720d-250122T062530"
  },
  {
    "_disabled": "false",
    "pkg": "oras",
    "pkg_family": "oras",
    "pkg_id": "github.com.oras-project.oras",
    "pkg_type": "static",
    "pkg_webpage": "https://pkgs.pkgforge.dev/repo/soarpkgs/project-oras/oras/oras",
    "bincache": "ghcr.io/pkgforge/bincache/oras/official/oras",
    "build_script": "https://github.com/pkgforge/soarpkgs/blob/main/binaries/oras/static.official.source.yaml",
    "category": [
      "ConsoleOnly",
      "Utility"
    ],
    "description": "OCI registry client - manage content like artifacts, images, packages",
    "distro_pkg": {
      "archlinux": {
        "aur": [
          "oras"
        ]
      },
      "debian": [
        "oras"
      ],
      "homebrew": [
        "oras"
      ],
      "nixpkgs": [
        "oras"
      ]
    },
    "download_url": "https://soarpkgs.pkgforge.dev/binaries/oras/static.official.source.yaml",
    "homepage": [
      "https://oras.land"
    ],
    "host": [
      "aarch64-linux",
      "x86_64-linux"
    ],
    "license": [
      "Apache-2.0"
    ],
    "maintainer": [
      "Azathothas (https://github.com/Azathothas)"
    ],
    "note": [
      "[DO NOT RUN] (Meant for pkgforge CI Only)",
      "Built From Source (Latest Git HEAD). Check/Report @ https://github.com/oras-project/oras"
    ],
    "provides": [
      "oras"
    ],
    "repology": [
      "oras"
    ],
    "src_url": [
      "https://github.com/oras-project/oras"
    ],
    "tag": [
      "oci",
      "registry"
    ],
    "version": "HEAD-13dce59-250122T050028"
  },
  {
    "_disabled": "false",
    "pkg": "pls",
    "pkg_family": "pls",
    "pkg_id": "github.com.pls-rs.pls",
    "pkg_type": "static",
    "pkg_webpage": "https://pkgs.pkgforge.dev/repo/soarpkgs/rs-pls/pls/pls",
    "bincache": "ghcr.io/pkgforge/bincache/pls/official/pls",
    "build_script": "https://github.com/pkgforge/soarpkgs/blob/main/binaries/pls/static.official.source.yaml",
    "category": [
      "ConsoleOnly",
      "Utility"
    ],
    "description": "A Prettier and Powerful ls(1) for the Pros",
    "distro_pkg": {
      "archlinux": {
        "aur": [
          "pls",
          "pls-git"
        ]
      },
      "nixpkgs": [
        "pls"
      ]
    },
    "download_url": "https://soarpkgs.pkgforge.dev/binaries/pls/static.official.source.yaml",
    "homepage": [
      "https://pls.cli.rs",
      "https://github.com/pls-rs/pls"
    ],
    "host": [
      "aarch64-linux",
      "x86_64-linux"
    ],
    "license": [
      "GPL3",
      "MIT"
    ],
    "maintainer": [
      "Azathothas (https://github.com/Azathothas)"
    ],
    "note": [
      "[DO NOT RUN] (Meant for pkgforge CI Only)",
      "Built From Source (Latest Git HEAD). Check/Report @ https://github.com/pls-rs/pls"
    ],
    "repology": [
      "pls"
    ],
    "src_url": [
      "https://github.com/pls-rs/pls"
    ],
    "tag": [
      "ls"
    ],
    "version": "HEAD-f14ad32-250122T175914"
  },
  {
    "_disabled": "false",
    "pkg": "rclone",
    "pkg_family": "rclone",
    "pkg_id": "github.com.rclone.rclone",
    "pkg_type": "static",
    "pkg_webpage": "https://pkgs.pkgforge.dev/repo/soarpkgs/rclone-rclone/rclone/rclone",
    "bincache": "ghcr.io/pkgforge/bincache/rclone/official/rclone",
    "build_script": "https://github.com/pkgforge/soarpkgs/blob/main/binaries/rclone/static.official.source.yaml",
    "category": [
      "ConsoleOnly",
      "Utility"
    ],
    "description": "A program to sync files to and from various cloud storage providers",
    "distro_pkg": {
      "alpine": [
        "rclone"
      ],
      "archlinux": {
        "aur": [
          "rclone-beta-bin",
          "rclone-git"
        ],
        "extra": [
          "rclone"
        ]
      },
      "debian": [
        "rclone"
      ],
      "homebrew": [
        "rclone"
      ],
      "nixpkgs": [
        "rclone"
      ]
    },
    "download_url": "https://soarpkgs.pkgforge.dev/binaries/rclone/static.official.source.yaml",
    "homepage": [
      "https://rclone.org",
      "https://github.com/rclone/rclone"
    ],
    "host": [
      "aarch64-linux",
      "x86_64-linux"
    ],
    "license": [
      "BSD",
      "ISC",
      "MIT"
    ],
    "maintainer": [
      "Azathothas (https://github.com/Azathothas)"
    ],
    "note": [
      "[DO NOT RUN] (Meant for pkgforge CI Only)",
      "Built From Source (Latest Git HEAD). Check/Report @ https://github.com/rclone/rclone"
    ],
    "repology": [
      "rclone"
    ],
    "src_url": [
      "https://github.com/rclone/rclone"
    ],
    "tag": [
      "cloud",
      "mount",
      "rsync",
      "s3",
      "sync"
    ],
    "version": "HEAD-c837664-250122T115605"
  },
  {
    "_disabled": "false",
    "pkg": "ripgrep",
    "pkg_family": "ripgrep",
    "pkg_id": "github.com.BurntSushi.ripgrep",
    "pkg_type": "static",
    "pkg_webpage": "https://pkgs.pkgforge.dev/repo/soarpkgs/burntsushi-ripgrep/ripgrep/ripgrep",
    "bincache": "ghcr.io/pkgforge/bincache/ripgrep/official/rg",
    "build_script": "https://github.com/pkgforge/soarpkgs/blob/main/binaries/ripgrep/static.official.source.yaml",
    "category": [
      "ConsoleOnly",
      "Utility"
    ],
    "description": "Recursive & Line-Oriented Search Tool, combining The Silver Searcher (ag) with the raw speed of grep",
    "distro_pkg": {
      "alpine": [
        "ripgrep"
      ],
      "archlinux": {
        "aur": [
          "ripgrep-git"
        ],
        "extra": [
          "ripgrep"
        ]
      },
      "debian": [
        "rust-ripgrep"
      ],
      "nixpkgs": [
        "ripgrep"
      ]
    },
    "download_url": "https://soarpkgs.pkgforge.dev/binaries/ripgrep/static.official.source.yaml",
    "homepage": [
      "https://github.com/BurntSushi/ripgrep"
    ],
    "host": [
      "aarch64-linux",
      "x86_64-linux"
    ],
    "license": [
      "MIT",
      "Unlicense"
    ],
    "maintainer": [
      "Azathothas (https://github.com/Azathothas)"
    ],
    "note": [
      "[DO NOT RUN] (Meant for pkgforge CI Only)",
      "Built From Source (Latest Git HEAD). Check/Report @ https://github.com/BurntSushi/ripgrep"
    ],
    "provides": [
      "ripgrep==rg"
    ],
    "repology": [
      "ripgrep"
    ],
    "src_url": [
      "https://github.com/BurntSushi/ripgrep"
    ],
    "tag": [
      "grep",
      "regex"
    ],
    "version": "HEAD-d6b59fe-250113T101609"
  },
  {
    "_disabled": "false",
    "pkg": "soar",
    "pkg_family": "soar",
    "pkg_id": "github.com.pkgforge.soar",
    "pkg_type": "static",
    "pkg_webpage": "https://pkgs.pkgforge.dev/repo/soarpkgs/pkgforge-soar/soar/soar",
    "bincache": "ghcr.io/pkgforge/bincache/soar/official/soar",
    "build_script": "https://github.com/pkgforge/soarpkgs/blob/main/binaries/soar/static.official.source.yaml",
    "category": [
      "ConsoleOnly",
      "Utility"
    ],
    "description": "The Modern, Bloat-Free Distro-Independent Package Manager",
    "distro_pkg": {
      "archlinux": {
        "aur": [
          "soar-bin"
        ]
      }
    },
    "download_url": "https://soarpkgs.pkgforge.dev/binaries/soar/static.official.source.yaml",
    "homepage": [
      "https://soar.qaidvoid.dev",
      "https://github.com/pkgforge/soar"
    ],
    "host": [
      "aarch64-linux",
      "x86_64-linux"
    ],
    "icon": "https://soarpkgs.pkgforge.dev/binaries/soar/assets/default.png",
    "license": [
      "MIT"
    ],
    "maintainer": [
      "Azathothas (https://github.com/Azathothas)"
    ],
    "note": [
      "[DO NOT RUN] (Meant for pkgforge CI Only)",
      "Built From Source (Latest Git HEAD). Check/Report @ https://github.com/pkgforge/soar"
    ],
    "repology": [
      "soar"
    ],
    "src_url": [
      "https://github.com/pkgforge/soar"
    ],
    "tag": [
      "package-manager"
    ],
    "version": "HEAD-63cf070-250121T213535"
  },
  {
    "_disabled": "false",
    "pkg": "yazi",
    "pkg_family": "yazi",
    "pkg_id": "github.com.sxyazi.yazi",
    "pkg_type": "static",
    "pkg_webpage": "https://pkgs.pkgforge.dev/repo/soarpkgs/sxyazi-yazi/yazi/yazi",
    "bincache": "ghcr.io/pkgforge/bincache/yazi/official/ya",
    "build_script": "https://github.com/pkgforge/soarpkgs/blob/main/binaries/yazi/static.official.source.yaml",
    "category": [
      "ConsoleOnly",
      "Utility"
    ],
    "description": {
      "_default": "Blazing fast terminal file manager",
      "ya": "CLI interface for yazi",
      "yazi": "Blazing fast terminal file manager"
    },
    "distro_pkg": {
      "alpine": [
        "yazi"
      ],
      "archlinux": {
        "aur": [
          "yazi-git"
        ],
        "extra": [
          "yazi"
        ]
      },
      "nixpkgs": [
        "yazi",
        "yazi-unwrapped"
      ]
    },
    "download_url": "https://soarpkgs.pkgforge.dev/binaries/yazi/static.official.source.yaml",
    "homepage": [
      "https://yazi-rs.github.io",
      "https://github.com/sxyazi/yazi"
    ],
    "host": [
      "aarch64-linux",
      "x86_64-linux"
    ],
    "license": [
      "BSD",
      "ISC",
      "MIT"
    ],
    "maintainer": [
      "Azathothas (https://github.com/Azathothas)"
    ],
    "note": [
      "[DO NOT RUN] (Meant for pkgforge CI Only)",
      "Built From Source (Latest Git HEAD). Check/Report @ https://github.com/sxyazi/yazi"
    ],
    "provides": [
      "ya",
      "yazi"
    ],
    "repology": [
      "yazi"
    ],
    "src_url": [
      "https://github.com/sxyazi/yazi"
    ],
    "tag": [
      "file",
      "explorer",
      "manager"
    ],
    "version": "HEAD-245fb03-250120T185900"
  }
]
